{"name":"hover-effect","h1":"Hover effect","icon":"i-star","dependencies":{},"languages":{"html":{"code":"<section id=\"set-1\">\n    <div class=\"hi-icon-wrap hi-icon-effect-1 hi-icon-effect-1a\">\n        <a href=\"#set-1\" class=\"hi-icon hi-icon-mobile\">Mobile<\/a>\n        <a href=\"#set-1\" class=\"hi-icon hi-icon-screen\">Desktop<\/a>\n        <a href=\"#set-1\" class=\"hi-icon hi-icon-earth\">Partners<\/a>\n        <a href=\"#set-1\" class=\"hi-icon hi-icon-support\">Support<\/a>\n        <a href=\"#set-1\" class=\"hi-icon hi-icon-locked\">Security<\/a>\n    <\/div>\n    <div class=\"hi-icon-wrap hi-icon-effect-1 hi-icon-effect-1b\">\n        <a href=\"#set-1\" class=\"hi-icon hi-icon-mobile\">Mobile<\/a>\n        <a href=\"#set-1\" class=\"hi-icon hi-icon-screen\">Desktop<\/a>\n        <a href=\"#set-1\" class=\"hi-icon hi-icon-earth\">Partners<\/a>\n        <a href=\"#set-1\" class=\"hi-icon hi-icon-support\">Support<\/a>\n        <a href=\"#set-1\" class=\"hi-icon hi-icon-locked\">Security<\/a>\n    <\/div>\n<\/section>\n<section id=\"set-2\">\n    <div class=\"hi-icon-wrap hi-icon-effect-2 hi-icon-effect-2a\">\n        <a href=\"#set-2\" class=\"hi-icon hi-icon-cog\">Settings<\/a>\n        <a href=\"#set-2\" class=\"hi-icon hi-icon-clock\">Time<\/a>\n        <a href=\"#set-2\" class=\"hi-icon hi-icon-videos\">Videos<\/a>\n        <a href=\"#set-2\" class=\"hi-icon hi-icon-list\">List<\/a>\n        <a href=\"#set-2\" class=\"hi-icon hi-icon-refresh\">Refresh<\/a>\n    <\/div>\n    <div class=\"hi-icon-wrap hi-icon-effect-2 hi-icon-effect-2b\">\n        <a href=\"#set-2\" class=\"hi-icon hi-icon-cog\">Settings<\/a>\n        <a href=\"#set-2\" class=\"hi-icon hi-icon-clock\">Time<\/a>\n        <a href=\"#set-2\" class=\"hi-icon hi-icon-videos\">Videos<\/a>\n        <a href=\"#set-2\" class=\"hi-icon hi-icon-list\">List<\/a>\n        <a href=\"#set-2\" class=\"hi-icon hi-icon-refresh\">Refresh<\/a>\n    <\/div>\n<\/section>\n<section id=\"set-3\">\n    <div class=\"hi-icon-wrap hi-icon-effect-3 hi-icon-effect-3a\">\n        <a href=\"#set-3\" class=\"hi-icon hi-icon-images\">Images<\/a>\n        <a href=\"#set-3\" class=\"hi-icon hi-icon-pencil\">Edit<\/a>\n        <a href=\"#set-3\" class=\"hi-icon hi-icon-link\">Link<\/a>\n        <a href=\"#set-3\" class=\"hi-icon hi-icon-mail\">Mail<\/a>\n        <a href=\"#set-3\" class=\"hi-icon hi-icon-location\">Location<\/a>\n    <\/div>\n    <div class=\"hi-icon-wrap hi-icon-effect-3 hi-icon-effect-3b\">\n        <a href=\"#set-3\" class=\"hi-icon hi-icon-images\">Images<\/a>\n        <a href=\"#set-3\" class=\"hi-icon hi-icon-pencil\">Edit<\/a>\n        <a href=\"#set-3\" class=\"hi-icon hi-icon-link\">Link<\/a>\n        <a href=\"#set-3\" class=\"hi-icon hi-icon-mail\">Mail<\/a>\n        <a href=\"#set-3\" class=\"hi-icon hi-icon-location\">Location<\/a>\n    <\/div>\n<\/section>\n<section id=\"set-4\">\n    <div class=\"hi-icon-wrap hi-icon-effect-4 hi-icon-effect-4a\">\n        <a href=\"#set-4\" class=\"hi-icon hi-icon-archive\">Archive<\/a>\n        <a href=\"#set-4\" class=\"hi-icon hi-icon-chat\">Chat<\/a>\n        <a href=\"#set-4\" class=\"hi-icon hi-icon-bookmark\">Bookmarks<\/a>\n        <a href=\"#set-4\" class=\"hi-icon hi-icon-user\">User<\/a>\n        <a href=\"#set-4\" class=\"hi-icon hi-icon-contract\">Contact<\/a>\n    <\/div>\n    <div class=\"hi-icon-wrap hi-icon-effect-4 hi-icon-effect-4b\">\n        <a href=\"#set-4\" class=\"hi-icon hi-icon-archive\">Archive<\/a>\n        <a href=\"#set-4\" class=\"hi-icon hi-icon-chat\">Chat<\/a>\n        <a href=\"#set-4\" class=\"hi-icon hi-icon-bookmark\">Bookmarks<\/a>\n        <a href=\"#set-4\" class=\"hi-icon hi-icon-user\">User<\/a>\n        <a href=\"#set-4\" class=\"hi-icon hi-icon-contract\">Contact<\/a>\n    <\/div>\n    <p>Note that the dashed border on a round pseudo-element (border-radius: 50%) does not work in FF 21.0<\/p>\n<\/section>\n<section id=\"set-5\">\n    <div class=\"hi-icon-wrap hi-icon-effect-5 hi-icon-effect-5a\">\n        <a href=\"#set-5\" class=\"hi-icon hi-icon-mobile\">Mobile<\/a>\n        <a href=\"#set-5\" class=\"hi-icon hi-icon-screen\">Desktop<\/a>\n        <a href=\"#set-5\" class=\"hi-icon hi-icon-earth\">Partners<\/a>\n        <a href=\"#set-5\" class=\"hi-icon hi-icon-support\">Support<\/a>\n        <a href=\"#set-5\" class=\"hi-icon hi-icon-locked\">Security<\/a>\n    <\/div>\n    <div class=\"hi-icon-wrap hi-icon-effect-5 hi-icon-effect-5b\">\n        <a href=\"#set-5\" class=\"hi-icon hi-icon-mobile\">Mobile<\/a>\n        <a href=\"#set-5\" class=\"hi-icon hi-icon-screen\">Desktop<\/a>\n        <a href=\"#set-5\" class=\"hi-icon hi-icon-earth\">Partners<\/a>\n        <a href=\"#set-5\" class=\"hi-icon hi-icon-support\">Support<\/a>\n        <a href=\"#set-5\" class=\"hi-icon hi-icon-locked\">Security<\/a>\n    <\/div>\n    <div class=\"hi-icon-wrap hi-icon-effect-5 hi-icon-effect-5c\">\n        <a href=\"#set-5\" class=\"hi-icon hi-icon-mobile\">Mobile<\/a>\n        <a href=\"#set-5\" class=\"hi-icon hi-icon-screen\">Desktop<\/a>\n        <a href=\"#set-5\" class=\"hi-icon hi-icon-earth\">Partners<\/a>\n        <a href=\"#set-5\" class=\"hi-icon hi-icon-support\">Support<\/a>\n        <a href=\"#set-5\" class=\"hi-icon hi-icon-locked\">Security<\/a>\n    <\/div>\n    <div class=\"hi-icon-wrap hi-icon-effect-5 hi-icon-effect-5d\">\n        <a href=\"#set-5\" class=\"hi-icon hi-icon-mobile\">Mobile<\/a>\n        <a href=\"#set-5\" class=\"hi-icon hi-icon-screen\">Desktop<\/a>\n        <a href=\"#set-5\" class=\"hi-icon hi-icon-earth\">Partners<\/a>\n        <a href=\"#set-5\" class=\"hi-icon hi-icon-support\">Support<\/a>\n        <a href=\"#set-5\" class=\"hi-icon hi-icon-locked\">Security<\/a>\n    <\/div>\n<\/section>\n<section id=\"set-6\">\n    <div class=\"hi-icon-wrap hi-icon-effect-6\">\n        <a href=\"#set-6\" class=\"hi-icon hi-icon-cog\">Settings<\/a>\n        <a href=\"#set-6\" class=\"hi-icon hi-icon-support\">Support<\/a>\n        <a href=\"#set-6\" class=\"hi-icon hi-icon-star\">Fav<\/a>\n        <a href=\"#set-6\" class=\"hi-icon hi-icon-contract\">Contract<\/a>\n        <a href=\"#set-6\" class=\"hi-icon hi-icon-refresh\">Refresh<\/a>\n    <\/div>\n<\/section>\n<section id=\"set-7\">\n    <div class=\"hi-icon-wrap hi-icon-effect-7 hi-icon-effect-7a\">\n        <a href=\"#set-7\" class=\"hi-icon hi-icon-cog\">Settings<\/a>\n        <a href=\"#set-7\" class=\"hi-icon hi-icon-clock\">Time<\/a>\n        <a href=\"#set-7\" class=\"hi-icon hi-icon-videos\">Videos<\/a>\n        <a href=\"#set-7\" class=\"hi-icon hi-icon-list\">List<\/a>\n        <a href=\"#set-7\" class=\"hi-icon hi-icon-refresh\">Refresh<\/a>\n    <\/div>\n    <div class=\"hi-icon-wrap hi-icon-effect-7 hi-icon-effect-7b\">\n        <a href=\"#set-7\" class=\"hi-icon hi-icon-cog\">Settings<\/a>\n        <a href=\"#set-7\" class=\"hi-icon hi-icon-clock\">Time<\/a>\n        <a href=\"#set-7\" class=\"hi-icon hi-icon-videos\">Videos<\/a>\n        <a href=\"#set-7\" class=\"hi-icon hi-icon-list\">List<\/a>\n        <a href=\"#set-7\" class=\"hi-icon hi-icon-refresh\">Refresh<\/a>\n    <\/div>\n<\/section>\n<section id=\"set-8\">\n    <div class=\"hi-icon-wrap hi-icon-effect-8\">\n        <a href=\"#set-8\" class=\"hi-icon hi-icon-archive\">Archive<\/a>\n        <a href=\"#set-8\" class=\"hi-icon hi-icon-chat\">Chat<\/a>\n        <a href=\"#set-8\" class=\"hi-icon hi-icon-bookmark\">Bookmarks<\/a>\n        <a href=\"#set-8\" class=\"hi-icon hi-icon-user\">User<\/a>\n        <a href=\"#set-8\" class=\"hi-icon hi-icon-contract\">Contact<\/a>\n    <\/div>\n<\/section>\n<section id=\"set-9\">\n    <div class=\"hi-icon-wrap hi-icon-effect-9 hi-icon-effect-9a\">\n        <a href=\"#set-9\" class=\"hi-icon hi-icon-images\">Images<\/a>\n        <a href=\"#set-9\" class=\"hi-icon hi-icon-pencil\">Edit<\/a>\n        <a href=\"#set-9\" class=\"hi-icon hi-icon-link\">Link<\/a>\n        <a href=\"#set-9\" class=\"hi-icon hi-icon-mail\">Mail<\/a>\n        <a href=\"#set-9\" class=\"hi-icon hi-icon-location\">Location<\/a>\n    <\/div>\n    <div class=\"hi-icon-wrap hi-icon-effect-9 hi-icon-effect-9b\">\n        <a href=\"#set-9\" class=\"hi-icon hi-icon-images\">Images<\/a>\n        <a href=\"#set-9\" class=\"hi-icon hi-icon-pencil\">Edit<\/a>\n        <a href=\"#set-9\" class=\"hi-icon hi-icon-link\">Link<\/a>\n        <a href=\"#set-9\" class=\"hi-icon hi-icon-mail\">Mail<\/a>\n        <a href=\"#set-9\" class=\"hi-icon hi-icon-location\">Location<\/a>\n    <\/div>\n<\/section>","label":"Html"},"css":{"code":"@font-face {\n\tfont-family: 'ecoicon';\n\tsrc:url('..\/fonts\/ecoicons\/ecoicon.eot');\n\tsrc:url('..\/fonts\/ecoicons\/ecoicon.eot?#iefix') format('embedded-opentype'),\n\t\turl('..\/fonts\/ecoicons\/ecoicon.woff') format('woff'),\n\t\turl('..\/fonts\/ecoicons\/ecoicon.ttf') format('truetype'),\n\t\turl('..\/fonts\/ecoicons\/ecoicon.svg#ecoicon') format('svg');\n\tfont-weight: normal;\n\tfont-style: normal;\n}\n\n.hi-icon-wrap {\n\ttext-align: center;\n\tmargin: 0 auto;\n\tpadding: 2em 0 3em;\n}\n\n.hi-icon {\n\tdisplay: inline-block;\n\tfont-size: 0px;\n\tcursor: pointer;\n\tmargin: 15px 30px;\n\twidth: 90px;\n\theight: 90px;\n\tborder-radius: 50%;\n\ttext-align: center;\n\tposition: relative;\n\tz-index: 1;\n\tcolor: #fff;\n}\n\n.hi-icon:after {\n\tpointer-events: none;\n\tposition: absolute;\n\twidth: 100%;\n\theight: 100%;\n\tborder-radius: 50%;\n\tcontent: '';\n\t-webkit-box-sizing: content-box; \n\t-moz-box-sizing: content-box; \n\tbox-sizing: content-box;\n}\n\n.hi-icon:before {\n\tfont-family: 'ecoicon';\n\tspeak: none;\n\tfont-size: 48px;\n\tline-height: 90px;\n\tfont-style: normal;\n\tfont-weight: normal;\n\tfont-variant: normal;\n\ttext-transform: none;\n\tdisplay: block;\n\t-webkit-font-smoothing: antialiased;\n}\n\n.hi-icon-mobile:before {\n\tcontent: \"\\e009\";\n}\n\n.hi-icon-screen:before {\n\tcontent: \"\\e00a\";\n}\n\n.hi-icon-earth:before {\n\tcontent: \"\\e002\";\n}\n\n.hi-icon-support:before {\n\tcontent: \"\\e000\";\n}\n\n.hi-icon-locked:before {\n\tcontent: \"\\e001\";\n}\n\n.hi-icon-cog:before {\n\tcontent: \"\\e003\";\n}\n\n.hi-icon-clock:before {\n\tcontent: \"\\e004\";\n}\n\n.hi-icon-videos:before {\n\tcontent: \"\\e005\";\n}\n\n.hi-icon-list:before {\n\tcontent: \"\\e006\";\n}\n\n.hi-icon-refresh:before {\n\tcontent: \"\\e007\";\n}\n\n.hi-icon-images:before {\n\tcontent: \"\\e008\";\n}\n\n.hi-icon-pencil:before {\n\tcontent: \"\\e00b\";\n}\n\n.hi-icon-link:before {\n\tcontent: \"\\e00c\";\n}\n\n.hi-icon-mail:before {\n\tcontent: \"\\e00d\";\n}\n\n.hi-icon-location:before {\n\tcontent: \"\\e00e\";\n}\n\n.hi-icon-archive:before {\n\tcontent: \"\\e00f\";\n}\n\n.hi-icon-chat:before {\n\tcontent: \"\\e010\";\n}\n\n.hi-icon-bookmark:before {\n\tcontent: \"\\e011\";\n}\n\n.hi-icon-user:before {\n\tcontent: \"\\e012\";\n}\n\n.hi-icon-contract:before {\n\tcontent: \"\\e013\";\n}\n\n.hi-icon-star:before {\n\tcontent: \"\\e014\";\n}\n\n\/* Effect 1 *\/\n.hi-icon-effect-1 .hi-icon {\n\tbackground: rgba(255,255,255,0.1);\n\t-webkit-transition: background 0.2s, color 0.2s;\n\t-moz-transition: background 0.2s, color 0.2s;\n\ttransition: background 0.2s, color 0.2s;\n}\n\n.hi-icon-effect-1 .hi-icon:after {\n\ttop: -7px;\n\tleft: -7px;\n\tpadding: 7px;\n\tbox-shadow: 0 0 0 4px #fff;\n\t-webkit-transition: -webkit-transform 0.2s, opacity 0.2s;\n\t-webkit-transform: scale(.8);\n\t-moz-transition: -moz-transform 0.2s, opacity 0.2s;\n\t-moz-transform: scale(.8);\n\t-ms-transform: scale(.8);\n\ttransition: transform 0.2s, opacity 0.2s;\n\ttransform: scale(.8);\n\topacity: 0;\n}\n\n\/* Effect 1a *\/\n.hi-icon-effect-1a .hi-icon:hover {\n\tbackground: rgba(255,255,255,1);\n\tcolor: #41ab6b;\n}\n\n.hi-icon-effect-1a .hi-icon:hover:after {\n\t-webkit-transform: scale(1);\n\t-moz-transform: scale(1);\n\t-ms-transform: scale(1);\n\ttransform: scale(1);\n\topacity: 1;\n}\n\n\/* Effect 1b *\/\n.hi-icon-effect-1b .hi-icon:hover {\n\tbackground: rgba(255,255,255,1);\n\tcolor: #41ab6b;\n}\n\n.hi-icon-effect-1b .hi-icon:after {\n\t-webkit-transform: scale(1.2);\n\t-moz-transform: scale(1.2);\n\t-ms-transform: scale(1.2);\n\ttransform: scale(1.2);\n}\n\n.hi-icon-effect-1b .hi-icon:hover:after {\n\t-webkit-transform: scale(1);\n\t-moz-transform: scale(1);\n\t-ms-transform: scale(1);\n\ttransform: scale(1);\n\topacity: 1;\n}\n\n\/* Effect 2 *\/\n.hi-icon-effect-2 .hi-icon {\n\tcolor: #eea303;\n\tbox-shadow: 0 0 0 3px #fff;\n\t-webkit-transition: color 0.3s;\n\t-moz-transition: color 0.3s;\n\ttransition: color 0.3s;\n}\n\n.hi-icon-effect-2 .hi-icon:after {\n\ttop: -2px;\n\tleft: -2px;\n\tpadding: 2px;\n\tz-index: -1;\n\tbackground: #fff;\n\t-webkit-transition: -webkit-transform 0.2s, opacity 0.2s;\n\t-moz-transition: -moz-transform 0.2s, opacity 0.2s;\n\ttransition: transform 0.2s, opacity 0.2s;\n}\n\n\/* Effect 2a *\/\n.hi-icon-effect-2a .hi-icon:hover {\n\tcolor: #eea303;\n}\n\n.hi-icon-effect-2a .hi-icon:hover:after {\n\t-webkit-transform: scale(0.85);\n\t-moz-transform: scale(0.85);\n\t-ms-transform: scale(0.85);\n\ttransform: scale(0.85);\n}\n\n\/* Effect 2b *\/\n.hi-icon-effect-2b .hi-icon:hover:after {\n\t-webkit-transform: scale(0);\n\t-moz-transform: scale(0);\n\t-ms-transform: scale(0);\n\ttransform: scale(0);\n\topacity: 0;\n\t-webkit-transition: -webkit-transform 0.4s, opacity 0.2s;\n\t-moz-transition: -moz-transform 0.4s, opacity 0.2s;\n\ttransition: transform 0.4s, opacity 0.2s;\n}\n\n.hi-icon-effect-2b .hi-icon:hover {\n\tcolor: #fff;\n}\n\n\/* Effect 3 *\/\n.hi-icon-effect-3 .hi-icon {\n\tbox-shadow: 0 0 0 4px #fff;\n\t-webkit-transition: color 0.3s;\n\t-moz-transition: color 0.3s;\n\ttransition: color 0.3s;\n}\n\n.hi-icon-effect-3 .hi-icon:after {\n\ttop: -2px;\n\tleft: -2px;\n\tpadding: 2px;\n\tz-index: -1;\n\tbackground: #fff;\n\t-webkit-transition: -webkit-transform 0.2s, opacity 0.3s;\n\t-moz-transition: -moz-transform 0.2s, opacity 0.3s;\n\ttransition: transform 0.2s, opacity 0.3s;\n}\n\n\/* Effect 3a *\/\n.hi-icon-effect-3a .hi-icon {\n\tcolor: #f06060;\n}\n\n.hi-icon-effect-3a .hi-icon:hover {\n\tcolor: #fff;\n}\n\n.hi-icon-effect-3a .hi-icon:hover:after {\n\t-webkit-transform: scale(1.3);\n\t-moz-transform: scale(1.3);\n\t-ms-transform: scale(1.3);\n\ttransform: scale(1.3);\n\topacity: 0;\n}\n\n\/* Effect 3b *\/\n.hi-icon-effect-3b .hi-icon {\n\tcolor: #fff;\n}\n\n.hi-icon-effect-3b .hi-icon:hover {\n\tcolor: #f06060;\n}\n\n.hi-icon-effect-3b .hi-icon:after {\n\t-webkit-transform: scale(1.3);\n\t-moz-transform: scale(1.3);\n\t-ms-transform: scale(1.3);\n\ttransform: scale(1.3);\n\topacity: 0;\n}\n\n.hi-icon-effect-3b .hi-icon:hover:after {\n\t-webkit-transform: scale(1);\n\t-moz-transform: scale(1);\n\t-ms-transform: scale(1);\n\ttransform: scale(1);\n\topacity: 1;\n}\n\n\/* Effect 4 *\/\n.hi-icon-effect-4 .hi-icon {\n\twidth: 92px;\n\theight: 92px;\n\tbox-shadow: 0 0 0 4px rgba(255,255,255,1);\t\n}\n\n.hi-icon-effect-4a .hi-icon {\n\t-webkit-transition: box-shadow 0.2s;\n\t-moz-transition: box-shadow 0.2s;\n\ttransition: box-shadow 0.2s;\n}\n\n.hi-icon-effect-4 .hi-icon:before {\n\tline-height: 92px;\n}\n\n.hi-icon-effect-4 .hi-icon:after {\n\ttop: -4px;\n\tleft: -4px;\n\tpadding: 0;\n\tz-index: 10;\n\tborder: 4px dashed #fff;\n}\n\n.hi-icon-effect-4 .hi-icon:hover {\n\tbox-shadow: 0 0 0 0 rgba(255,255,255,0);\n\tcolor: #fff;\n}\n\n\/* Effect 4b *\/\n.hi-icon-effect-4b .hi-icon:hover {\n\t-webkit-transition: box-shadow 0.2s;\n\t-moz-transition: box-shadow 0.2s;\n\ttransition: box-shadow 0.2s;\n}\n\n.hi-icon-effect-4b .hi-icon:hover:after {\n\t-webkit-animation: spinAround 9s linear infinite;\n\t-moz-animation: spinAround 9s linear infinite;\n\tanimation: spinAround 9s linear infinite;\n}\n\n@-webkit-keyframes spinAround {\n\tfrom {\n\t\t-webkit-transform: rotate(0deg)\n\t}\n\tto {\n\t\t-webkit-transform: rotate(360deg);\n\t}\n}\n@-moz-keyframes spinAround {\n\tfrom {\n\t\t-moz-transform: rotate(0deg)\n\t}\n\tto {\n\t\t-moz-transform: rotate(360deg);\n\t}\n}\n@keyframes spinAround {\n\tfrom {\n\t\ttransform: rotate(0deg)\n\t}\n\tto {\n\t\ttransform: rotate(360deg);\n\t}\n}\n\n\/* Effect 5 *\/\n.hi-icon-effect-5 .hi-icon {\n\tbox-shadow: 0 0 0 4px rgba(255,255,255,1);\n\toverflow: hidden;\n\t-webkit-transition: background 0.3s, color 0.3s, box-shadow 0.3s;\n\t-moz-transition: background 0.3s, color 0.3s, box-shadow 0.3s;\n\ttransition: background 0.3s, color 0.3s, box-shadow 0.3s;\n}\n\n.hi-icon-effect-5 .hi-icon:after {\n\tdisplay: none;\n}\n\n.hi-icon-effect-5 .hi-icon:hover {\n\tbackground: rgba(255,255,255,1);\n\tcolor: #702fa8;\n\tbox-shadow: 0 0 0 8px rgba(255,255,255,0.3);\n}\n\n.hi-icon-effect-5a .hi-icon:hover:before {\n\t-webkit-animation: toRightFromLeft 0.3s forwards;\n\t-moz-animation: toRightFromLeft 0.3s forwards;\n\tanimation: toRightFromLeft 0.3s forwards;\n}\n\n@-webkit-keyframes toRightFromLeft {\n\t49% {\n\t\t-webkit-transform: translate(100%);\n\t}\n\t50% {\n\t\topacity: 0;\n\t\t-webkit-transform: translate(-100%);\n\t}\n\t51% {\n\t\topacity: 1;\n\t}\n}\n@-moz-keyframes toRightFromLeft {\n\t49% {\n\t\t-moz-transform: translate(100%);\n\t}\n\t50% {\n\t\topacity: 0;\n\t\t-moz-transform: translate(-100%);\n\t}\n\t51% {\n\t\topacity: 1;\n\t}\n}\n@keyframes toRightFromLeft {\n\t49% {\n\t\ttransform: translate(100%);\n\t}\n\t50% {\n\t\topacity: 0;\n\t\ttransform: translate(-100%);\n\t}\n\t51% {\n\t\topacity: 1;\n\t}\n}\n\n.hi-icon-effect-5b .hi-icon:hover:before {\n\t-webkit-animation: toLeftFromRight 0.3s forwards;\n\t-moz-animation: toLeftFromRight 0.3s forwards;\n\tanimation: toLeftFromRight 0.3s forwards;\n}\n\n@-webkit-keyframes toLeftFromRight {\n\t49% {\n\t\t-webkit-transform: translate(-100%);\n\t}\n\t50% {\n\t\topacity: 0;\n\t\t-webkit-transform: translate(100%);\n\t}\n\t51% {\n\t\topacity: 1;\n\t}\n}\n@-moz-keyframes toLeftFromRight {\n\t49% {\n\t\t-moz-transform: translate(-100%);\n\t}\n\t50% {\n\t\topacity: 0;\n\t\t-moz-transform: translate(100%);\n\t}\n\t51% {\n\t\topacity: 1;\n\t}\n}\n@keyframes toLeftFromRight {\n\t49% {\n\t\ttransform: translate(-100%);\n\t}\n\t50% {\n\t\topacity: 0;\n\t\ttransform: translate(100%);\n\t}\n\t51% {\n\t\topacity: 1;\n\t}\n}\n\n.hi-icon-effect-5c .hi-icon:hover:before {\n\t-webkit-animation: toTopFromBottom 0.3s forwards;\n\t-moz-animation: toTopFromBottom 0.3s forwards;\n\tanimation: toTopFromBottom 0.3s forwards;\n}\n\n@-webkit-keyframes toTopFromBottom {\n\t49% {\n\t\t-webkit-transform: translateY(-100%);\n\t}\n\t50% {\n\t\topacity: 0;\n\t\t-webkit-transform: translateY(100%);\n\t}\n\t51% {\n\t\topacity: 1;\n\t}\n}\n@-moz-keyframes toTopFromBottom {\n\t49% {\n\t\t-moz-transform: translateY(-100%);\n\t}\n\t50% {\n\t\topacity: 0;\n\t\t-moz-transform: translateY(100%);\n\t}\n\t51% {\n\t\topacity: 1;\n\t}\n}\n@keyframes toTopFromBottom {\n\t49% {\n\t\ttransform: translateY(-100%);\n\t}\n\t50% {\n\t\topacity: 0;\n\t\ttransform: translateY(100%);\n\t}\n\t51% {\n\t\topacity: 1;\n\t}\n}\n\n.hi-icon-effect-5d .hi-icon:hover:before {\n\t-webkit-animation: toBottomFromTop 0.3s forwards;\n\t-moz-animation: toBottomFromTop 0.3s forwards;\n\tanimation: toBottomFromTop 0.3s forwards;\n}\n\n@-webkit-keyframes toBottomFromTop {\n\t49% {\n\t\t-webkit-transform: translateY(100%);\n\t}\n\t50% {\n\t\topacity: 0;\n\t\t-webkit-transform: translateY(-100%);\n\t}\n\t51% {\n\t\topacity: 1;\n\t}\n}\n@-moz-keyframes toBottomFromTop {\n\t49% {\n\t\t-moz-transform: translateY(100%);\n\t}\n\t50% {\n\t\topacity: 0;\n\t\t-moz-transform: translateY(-100%);\n\t}\n\t51% {\n\t\topacity: 1;\n\t}\n}\n@keyframes toBottomFromTop {\n\t49% {\n\t\ttransform: translateY(100%);\n\t}\n\t50% {\n\t\topacity: 0;\n\t\ttransform: translateY(-100%);\n\t}\n\t51% {\n\t\topacity: 1;\n\t}\n}\n\n\/* Effect 6 *\/\n.hi-icon-effect-6 .hi-icon {\n\tbox-shadow: 0 0 0 4px rgba(255,255,255,1);\n\t-webkit-transition: background 0.2s, color 0.2s;\n\t-moz-transition: background 0.2s, color 0.2s;\n\ttransition: background 0.2s, color 0.2s;\n}\n\n.hi-icon-effect-6 .hi-icon:hover {\n\tbackground: rgba(255,255,255,1);\n\tcolor: #64bb5d;\n}\n\n.hi-icon-effect-6 .hi-icon:hover:before {\n\t-webkit-animation: spinAround 2s linear infinite;\n\t-moz-animation: spinAround 2s linear infinite;\n\tanimation: spinAround 2s linear infinite;\n}\n\n\/* Effect 7 *\/\n.hi-icon-effect-7 .hi-icon {\n\tbox-shadow: 0 0 0 4px rgba(255,255,255,1);\n\t-webkit-transition: background 0.2s, color 0.2s;\n\t-moz-transition: background 0.2s, color 0.2s;\n\ttransition: background 0.2s, color 0.2s;\t\n}\n\n.hi-icon-effect-7 .hi-icon:hover {\n\tcolor: #fff;\n}\n\n.hi-icon-effect-7 .hi-icon:after {\n\ttop: -8px;\n\tleft: -8px;\n\tpadding: 8px;\n\tz-index: -1;\n\topacity: 0;\n}\n\n\/* Effect 7a *\/\n.hi-icon-effect-7a .hi-icon:after {\n\tbox-shadow: 0 0 0 rgba(255,255,255,1);\n\t-webkit-transition: opacity 0.2s, box-shadow 0.2s;\n\t-moz-transition: opacity 0.2s, box-shadow 0.2s;\n\ttransition: opacity 0.2s, box-shadow 0.2s;\n}\n\n.hi-icon-effect-7a .hi-icon:hover:after {\n\topacity: 1;\n\tbox-shadow: 3px 3px 0 rgba(255,255,255,1);\n}\n\n.hi-icon-effect-7a .hi-icon:before {\n\t-webkit-transform: scale(0.8);\n\t-moz-transform: scale(0.8);\n\t-ms-transform: scale(0.8);\n\ttransform: scale(0.8);\n\topacity: 0.7;\n\t-webkit-transition: -webkit-transform 0.2s, opacity 0.2s;\n\t-moz-transition: -moz-transform 0.2s, opacity 0.2s;\n\ttransition: transform 0.2s, opacity 0.2s;\n}\n\n.hi-icon-effect-7a .hi-icon:hover:before {\n\t-webkit-transform: scale(1);\n\t-moz-transform: scale(1);\n\t-ms-transform: scale(1);\n\ttransform: scale(1);\n\topacity: 1;\n}\n\n\/* Effect 7b *\/\n.hi-icon-effect-7b .hi-icon:after {\n\tbox-shadow: 3px 3px rgba(255,255,255,1);\n\t-webkit-transform: rotate(-90deg);\n\t-moz-transform: rotate(-90deg);\n\t-ms-transform: rotate(-90deg);\n\ttransform: rotate(-90deg);\n\t-webkit-transition: opacity 0.2s, -webkit-transform 0.2s;\n\t-moz-transition: opacity 0.2s, -moz-transform 0.2s;\n\ttransition: opacity 0.2s, transform 0.2s;\n}\n\n.hi-icon-effect-7b .hi-icon:hover:after {\n\topacity: 1;\n\t-webkit-transform: rotate(0deg);\n\t-moz-transform: rotate(0deg);\n\t-ms-transform: rotate(0deg);\n\ttransform: rotate(0deg);\n}\n\n.hi-icon-effect-7b .hi-icon:before {\n\t-webkit-transform: scale(0.8);\n\t-moz-transform: scale(0.8);\n\t-ms-transform: scale(0.8);\n\ttransform: scale(0.8);\n\topacity: 0.7;\n\t-webkit-transition: -webkit-transform 0.2s, opacity 0.2s;\n\t-moz-transition: -moz-transform 0.2s, opacity 0.2s;\n\ttransition: transform 0.2s, opacity 0.2s;\n}\n\n.hi-icon-effect-7b .hi-icon:hover:before {\n\t-webkit-transform: scale(1);\n\t-moz-transform: scale(1);\n\t-ms-transform: scale(1);\n\ttransform: scale(1);\n\topacity: 1;\n}\n\n\/* Effect 8 *\/\n.hi-icon-effect-8 .hi-icon {\n\tbackground: rgba(255,255,255,0.1);\n\t-webkit-transition: -webkit-transform ease-out 0.1s, background 0.2s;\n\t-moz-transition: -moz-transform ease-out 0.1s, background 0.2s;\n\ttransition: transform ease-out 0.1s, background 0.2s;\n}\n\n.hi-icon-effect-8 .hi-icon:after {\n\ttop: 0;\n\tleft: 0;\n\tpadding: 0;\n\tz-index: -1;\n\tbox-shadow: 0 0 0 2px rgba(255,255,255,0.1);\n\topacity: 0;\n\t-webkit-transform: scale(0.9);\n\t-moz-transform: scale(0.9);\n\t-ms-transform: scale(0.9);\n\ttransform: scale(0.9);\n}\n\n.hi-icon-effect-8 .hi-icon:hover {\n\tbackground: rgba(255,255,255,0.05);\n\t-webkit-transform: scale(0.93);\n\t-moz-transform: scale(0.93);\n\t-ms-transform: scale(0.93);\n\ttransform: scale(0.93);\n\tcolor: #fff;\n}\n\n.hi-icon-effect-8 .hi-icon:hover:after {\n\t-webkit-animation: sonarEffect 1.3s ease-out 75ms;\n\t-moz-animation: sonarEffect 1.3s ease-out 75ms;\n\tanimation: sonarEffect 1.3s ease-out 75ms;\n}\n\n@-webkit-keyframes sonarEffect {\n\t0% {\n\t\topacity: 0.3;\n\t}\n\t40% {\n\t\topacity: 0.5;\n\t\tbox-shadow: 0 0 0 2px rgba(255,255,255,0.1), 0 0 10px 10px #3851bc, 0 0 0 10px rgba(255,255,255,0.5);\n\t}\n\t100% {\n\t\tbox-shadow: 0 0 0 2px rgba(255,255,255,0.1), 0 0 10px 10px #3851bc, 0 0 0 10px rgba(255,255,255,0.5);\n\t\t-webkit-transform: scale(1.5);\n\t\topacity: 0;\n\t}\n}\n@-moz-keyframes sonarEffect {\n\t0% {\n\t\topacity: 0.3;\n\t}\n\t40% {\n\t\topacity: 0.5;\n\t\tbox-shadow: 0 0 0 2px rgba(255,255,255,0.1), 0 0 10px 10px #3851bc, 0 0 0 10px rgba(255,255,255,0.5);\n\t}\n\t100% {\n\t\tbox-shadow: 0 0 0 2px rgba(255,255,255,0.1), 0 0 10px 10px #3851bc, 0 0 0 10px rgba(255,255,255,0.5);\n\t\t-moz-transform: scale(1.5);\n\t\topacity: 0;\n\t}\n}\n@keyframes sonarEffect {\n\t0% {\n\t\topacity: 0.3;\n\t}\n\t40% {\n\t\topacity: 0.5;\n\t\tbox-shadow: 0 0 0 2px rgba(255,255,255,0.1), 0 0 10px 10px #3851bc, 0 0 0 10px rgba(255,255,255,0.5);\n\t}\n\t100% {\n\t\tbox-shadow: 0 0 0 2px rgba(255,255,255,0.1), 0 0 10px 10px #3851bc, 0 0 0 10px rgba(255,255,255,0.5);\n\t\ttransform: scale(1.5);\n\t\topacity: 0;\n\t}\n}\n\n\/* Effect 9 *\/\n.hi-icon-effect-9 .hi-icon {\n\t-webkit-transition: box-shadow 0.2s;\n\t-moz-transition: box-shadow 0.2s;\n\ttransition: box-shadow 0.2s;\n}\n\n.hi-icon-effect-9 .hi-icon:after {\n\ttop: 0;\n\tleft: 0;\n\tpadding: 0;\n\tbox-shadow: 0 0 0 3px #fff;\n\t-webkit-transition: -webkit-transform 0.2s, opacity 0.2s;\n\t-moz-transition: -moz-transform 0.2s, opacity 0.2s;\n\ttransition: transform 0.2s, opacity 0.2s;\n}\n\n\/* Effect 9a *\/\n.hi-icon-effect-9a .hi-icon:hover:after {\n\t-webkit-transform: scale(0.85);\n\t-moz-transform: scale(0.85);\n\t-ms-transform: scale(0.85);\n\ttransform: scale(0.85);\n\topacity: 0.5;\n}\n\n.hi-icon-effect-9a .hi-icon:hover {\n\tbox-shadow: 0 0 0 10px rgba(255,255,255,1);\n\tcolor: #fff;\n}\n\n\/* Effect 9b *\/\n.hi-icon-effect-9b .hi-icon:hover:after {\n\t-webkit-transform: scale(0.85);\n\t-moz-transform: scale(0.85);\n\t-ms-transform: scale(0.85);\n\ttransform: scale(0.85);\n}\n\n.hi-icon-effect-9b .hi-icon:hover {\n\tbox-shadow: 0 0 0 10px rgba(255,255,255,0.4);\n\tcolor: #fff;\n}\n\n","label":"Css"}}}